{
  "project_info": {
    "project_number": "523215979340",
    "project_id": "otp-verfiyed",
    "storage_bucket": "otp-verfiyed.appspot.com"
  },
  "client": [
    {
      "client_info": {
        "mobilesdk_app_id": "1:523215979340:android:cbcb241c5f1e2a8d9f05e9",
        "android_client_info": {
          "package_name": "com.example.otpverification"
        }
      },
      "oauth_client": [],
      "api_key": [
        {
          "current_key": "AIzaSyBLr4Yg9CPTrhXkHt97CGtienWse11pEhA"
        }
      ],
      "services": {
        "appinvite_service": {
          "other_platform_oauth_client": []
        }
      }
    }
  ],
  "configuration_version": "1"
}